agms
